skjax/__init__.py
skjax/clustering.py
skjax/decomposition.py
skjax/linear_model.py
skjax/naive_bayes.py
skjax/_utils/__init__.py
skjax/_utils/_helper_functions.py
skjax/_utils/config.py
scikit_jax-0.0.1.dist-info/LICENSE.txt
scikit_jax-0.0.1.dist-info/METADATA
scikit_jax-0.0.1.dist-info/WHEEL
scikit_jax-0.0.1.dist-info/top_level.txt
scikit_jax-0.0.1.dist-info/RECORD
