Metadata-Version: 2.1
Name: scikit-jax
Version: 0.0.1
Summary: Classical machine learning algorithms on the GPU.
Home-page: https://github.com/LiibanMo/scikit-jax
Author: Liiban Mohamud
Author-email: liibanmohamud12@gmail.com
Keywords: jax classical machine learning
Classifier: Development Status :: 3 - Alpha
Classifier: Intended Audience :: Developers
Classifier: Intended Audience :: Science/Research
Classifier: Intended Audience :: Education
Classifier: Topic :: Software Development :: Build Tools
Classifier: Topic :: Scientific/Engineering :: Artificial Intelligence
Classifier: License :: OSI Approved :: MIT License
Classifier: Programming Language :: Python :: 3
Requires-Python: >=3.9
License-File: LICENSE.txt
Requires-Dist: jax
Requires-Dist: pandas
Requires-Dist: numpy
Requires-Dist: matplotlib
Requires-Dist: seaborn
